alu.v

/*----------------------------------------------------------------
Filename: alu.v
Function: 设计一个N位的ALU(实现两个N位有符号整数加 减 比较运算)
-----------------------------------------------------------------*/
module alu(ena, clk, opcode, data1, data2, y);
    //定义alu位宽
    parameter N = 8; //输入范围[-128, 127]
    
    //定义输入输出端口
    input ena, clk;
    input [1 : 0] opcode;
    input signed [N - 1 : 0] data1, data2; //输入有符号整数范围为[-128, 127] 
    output signed [N : 0] y; //输出范围有符号整数范围为[-255, 255]
    
    //内部寄存器定义
    reg signed [N : 0] y;
    
    //状态编码
    parameter ADD = 2'b00, SUB = 2'b01, COMPARE = 2'b10;
    
    //逻辑实现
    always@(posedge clk)
    begin
        if(ena)
        begin
            casex(opcode)
                ADD: y <= data1 + data2; //实现有符号整数加运算
                SUB: y <= data1 - data2; //实现有符号数减运算
                COMPARE: y <= (data1 > data2) ? 1 : ((data1 == data2) ? 0 : 2); //data1 = data2 输出0; data1 > data2 输出1; data1 < data2 输出2;
                default: y <= 0;
            endcase
        end
    end
endmodule

alu_t.v

/*------------------------------------
Filename: alu_t.v
Function: 测试alu模块的逻辑功能的测试用例
------------------------------------*/
`timescale 1ns/1ns
`define half_period 5
module alu_t(y);
    //alu位宽定义
    parameter N = 8;
    
    //输出端口定义
    output signed [N : 0] y;
    
    //寄存器及连线定义
    reg ena, clk;
    reg [1 : 0] opcode;
    reg signed [N - 1 : 0] data1, data2;
    
    //产生测试信号
    initial
    begin
        $dumpfile("aly_t.vcd");
        $dumpvars(0,alu_t);
        $display("my alu test");
        //设置电路初始状态
        #10 clk = 0; ena = 0; opcode = 2'b00;
            data1 = 8'd0; data2 = 8'd0;
        #10 ena = 1;
        
        //第一组测试
        #10 data1 = 8'd8; data2 = 8'd6; //y = 8 + 5 = 14
        #20 opcode = 2'b01; // y = 8 - 6 = 2
        #20 opcode = 2'b10; // 8 > 6 y = 1
        
        //第二组测试
        #10 data1 = 8'd127; data2 = 8'd127; opcode = 2'b00; //y = 127 + 127 = 254
        #20 opcode = 2'b01; //y = 127 - 127 = 0
        #20 opcode = 2'b10; // 127 == 127 y = 0
        
        //第三组测试
        #10 data1 = -8'd128; data2 = -8'd128; opcode = 2'b00; //y = -128 + -128 = -256
        #20 opcode = 2'b01; //y = -128 - (-128) = 0
        #20 opcode = 2'b10; // -128 == -128 y = 0
        
        //第四组测试
        #10 data1 = -8'd53; data2 = 8'd52; opcode = 2'b00; //y = -53 + 52 = -1
        #20 opcode = 2'b01; //y = -53 - 52 = -105
        #20 opcode = 2'b10; //-53 < 52 y = 2
        
        #100 $finish;
    end
    
    //产生时钟
    always #`half_period clk = ~clk;
    
    //实例化
    alu m0(.ena(ena), .clk(clk), .opcode(opcode), .data1(data1), .data2(data2), .y(y));
endmodule

aly_t.vcd
$date
	Thu Dec 29 17:15:32 2022
$end
$version
	Icarus Verilog
$end
$timescale
	1ns
$end
$scope module alu_t $end
$var wire 9 ! y [8:0] $end
$var parameter 32 " N $end
$var reg 1 # clk $end
$var reg 8 $ data1 [7:0] $end
$var reg 8 % data2 [7:0] $end
$var reg 1 & ena $end
$var reg 2 ' opcode [1:0] $end
$scope module m0 $end
$var wire 1 # clk $end
$var wire 8 ( data1 [7:0] $end
$var wire 8 ) data2 [7:0] $end
$var wire 1 & ena $end
$var wire 2 * opcode [1:0] $end
$var parameter 2 + ADD $end
$var parameter 2 , COMPARE $end
$var parameter 32 - N $end
$var parameter 2 . SUB $end
$var reg 9 / y [8:0] $end
$upscope $end
$upscope $end
$enddefinitions $end
$comment Show the parameter values. $end
$dumpall
b1 .
b1000 -
b10 ,
b0 +
b1000 "
$end
#0
$dumpvars
bx /
bx *
bx )
bx (
bx '
x&
bx %
bx $
x#
bx !
$end
#10
b0 %
b0 )
b0 $
b0 (
b0 '
b0 *
0&
1#
#15
0#
#20
b0 !
b0 /
1#
1&
#25
0#
#30
b1110 !
b1110 /
1#
b110 %
b110 )
b1000 $
b1000 (
#35
0#
#40
1#
#45
0#
#50
b10 !
b10 /
1#
b1 '
b1 *
#55
0#
#60
1#
#65
0#
#70
b1 !
b1 /
1#
b10 '
b10 *
#75
0#
#80
b11111110 !
b11111110 /
1#
b0 '
b0 *
b1111111 %
b1111111 )
b1111111 $
b1111111 (
#85
0#
#90
1#
#95
0#
#100
b0 !
b0 /
1#
b1 '
b1 *
#105
0#
#110
1#
#115
0#
#120
1#
b10 '
b10 *
#125
0#
#130
b100000000 !
b100000000 /
1#
b0 '
b0 *
b10000000 %
b10000000 )
b10000000 $
b10000000 (
#135
0#
#140
1#
#145
0#
#150
b0 !
b0 /
1#
b1 '
b1 *
#155
0#
#160
1#
#165
0#
#170
1#
b10 '
b10 *
#175
0#
#180
b111111111 !
b111111111 /
1#
b0 '
b0 *
b110100 %
b110100 )
b11001011 $
b11001011 (
#185
0#
#190
1#
#195
0#
#200
b110010111 !
b110010111 /
1#
b1 '
b1 *
#205
0#
#210
1#
#215
0#
#220
b10 !
b10 /
1#
b10 '
b10 *
